amanda_rerp_ols/__init__.py
amanda_rerp_ols/my_functions.py
amanda_rerp_ols-0.0.2.dist-info/LICENSE
amanda_rerp_ols-0.0.2.dist-info/METADATA
amanda_rerp_ols-0.0.2.dist-info/WHEEL
amanda_rerp_ols-0.0.2.dist-info/top_level.txt
amanda_rerp_ols-0.0.2.dist-info/RECORD
